khquizgen/__init__.py
khquizgen/__main__.py
khquizgen/config/settings.toml
khquizgen/config/settings.toml.backuo
khquizgen/inputs/KahootQuizTemplate.xlsx
khquizgen/inputs/questions.txt
khquizgen/quizgen.py
khquizgen/src/gen_quiz.py
khquizgen/src/parse_questions.py
khquizgen/src/use_template.py
khquizgen/src/utils.py
khquizgen-2.1.0.dist-info/LICENSE
khquizgen-2.1.0.dist-info/WHEEL
khquizgen-2.1.0.dist-info/METADATA
khquizgen-2.1.0.dist-info/RECORD
