Metadata-Version: 2.1
Name: khquizgen
Version: 2.1.0
Summary: Package to randomly autogenerate Kahoot quizzes from notes.
License: MIT
Author: BGASM
Author-email: slatte26@msu.edu
Requires-Python: >=3.8,<4.0
Classifier: License :: OSI Approved :: MIT License
Classifier: Programming Language :: Python :: 3
Classifier: Programming Language :: Python :: 3.8
Classifier: Programming Language :: Python :: 3.9
Requires-Dist: dynaconf (>=3.1.4,<4.0.0)
Requires-Dist: jellyfish (>=0.8.2,<0.9.0)
Requires-Dist: loguru (>=0.5.3,<0.6.0)
Requires-Dist: openpyxl (>=3.0.7,<4.0.0)
Requires-Dist: pandas (>=1.2.3,<2.0.0)
